cltl/mention_extraction/__init__.py
cltl/mention_extraction/api.py
cltl/mention_extraction/default_extractor.py
cltl/mention_extraction/object_label_translation.py
cltl/nlp/__init__.py
cltl/nlp/add_nlp_to_emissor.py
cltl/nlp/api.py
cltl/nlp/spacy_nlp.py
cltl.mention_detection-0.0.dev1.data/data/VERSION/VERSION
cltl_service/mention_extraction/__init__.py
cltl_service/mention_extraction/service.py
cltl_service/nlp/__init__.py
cltl_service/nlp/service.py
cltl.mention_detection-0.0.dev1.dist-info/LICENSE
cltl.mention_detection-0.0.dev1.dist-info/METADATA
cltl.mention_detection-0.0.dev1.dist-info/WHEEL
cltl.mention_detection-0.0.dev1.dist-info/top_level.txt
cltl.mention_detection-0.0.dev1.dist-info/RECORD
